kale/__init__.py
kale/kale.py
sc_kale-1.0.0.dist-info/METADATA
sc_kale-1.0.0.dist-info/WHEEL
sc_kale-1.0.0.dist-info/top_level.txt
sc_kale-1.0.0.dist-info/RECORD
