Metadata-Version: 2.4
Name: sc-kale
Version: 1.0.0
Summary: KALE: Cell Activity Inference Landscape
Author-email: Kisan Thapa <kisan.thapa001@umb.edu>, Ozgun Babur <ozgun.babur@umb.edu>
Project-URL: Homepage, https://github.com/KisanThapa/kale
Project-URL: Bug Tracker, https://github.com/KisanThapa/kale/issues
Classifier: Programming Language :: Python :: 3
Classifier: License :: OSI Approved :: MIT License
Classifier: Operating System :: OS Independent
Requires-Python: >=3.12
Requires-Dist: numpy>=2.3.2
Requires-Dist: pandas>=2.0.0
Requires-Dist: scanpy>=1.10.0
Requires-Dist: joblib>=1.5.1
Requires-Dist: anndata>=0.9.0
Requires-Dist: scipy>=1.10.0
Requires-Dist: requests>=2.28.0
Requires-Dist: tqdm>=4.65.0
Requires-Dist: setuptools>=61.0
Requires-Dist: twine>=6.1.0
Requires-Dist: build>=1.3.0
